{
  "packages": {
    ".": {
      "release-type": "node",
      "bump-minor-pre-major": true,
      "bump-patch-for-minor-pre-major": true,
      "changelog-sections": [
        { "type": "feat", "section": "Features" },
        { "type": "fix", "section": "Bug Fixes" },
        { "type": "perf", "section": "Performance" },
        { "type": "refactor", "section": "Code Refactoring" },
        { "type": "security", "section": "Security" },
        { "type": "test", "section": "Tests" },
        { "type": "docs", "section": "Documentation" },
        { "type": "chore", "section": "Miscellaneous" },
        { "type": "devops", "section": "DevOps" }
      ]
    }
  },
  "$schema": "https://raw.githubusercontent.com/googleapis/release-please/main/schemas/config.json"
}
